landscape/__init__.py
landscape/biomes.py
landscape/generation.py
landscape/main.py
landscape/rendering.py
landscape/signature.py
landscape/textures.py
landscape/utils.py
landscape/atmosphere/__init__.py
landscape/atmosphere/composition.py
landscape/atmosphere/filters.py
landscape/atmosphere/season.py
landscape/atmosphere/time.py
landscape/atmosphere/weather.py
landscape-0.1.1.dist-info/METADATA
landscape-0.1.1.dist-info/WHEEL
landscape-0.1.1.dist-info/entry_points.txt
landscape-0.1.1.dist-info/licenses/LICENSE
landscape-0.1.1.dist-info/RECORD
